dentity/__init__.py
dentity/__main__.py
dentity/access_management_service.py
dentity/connect_service.py
dentity/credential_service.py
dentity/dentity_service.py
dentity/dentity_util.py
dentity/file_management_service.py
dentity/provider_service.py
dentity/service_base.py
dentity/template_service.py
dentity/trustregistry_service.py
dentity/wallet_service.py
dentity/proto/__init__.py
dentity/proto/google/__init__.py
dentity/proto/google/api/__init__.py
dentity/proto/sdk/__init__.py
dentity/proto/sdk/options/__init__.py
dentity/proto/sdk/options/v1/__init__.py
dentity/proto/services/__init__.py
dentity/proto/services/account/__init__.py
dentity/proto/services/account/v1/__init__.py
dentity/proto/services/common/__init__.py
dentity/proto/services/common/v1/__init__.py
dentity/proto/services/connect/__init__.py
dentity/proto/services/connect/v1/__init__.py
dentity/proto/services/filemanagement/__init__.py
dentity/proto/services/filemanagement/v1/__init__.py
dentity/proto/services/options/__init__.py
dentity/proto/services/provider/__init__.py
dentity/proto/services/provider/v1/__init__.py
dentity/proto/services/trustregistry/__init__.py
dentity/proto/services/trustregistry/v1/__init__.py
dentity/proto/services/universalwallet/__init__.py
dentity/proto/services/universalwallet/v1/__init__.py
dentity/proto/services/verifiablecredentials/__init__.py
dentity/proto/services/verifiablecredentials/templates/__init__.py
dentity/proto/services/verifiablecredentials/templates/v1/__init__.py
dentity/proto/services/verifiablecredentials/v1/__init__.py
duyvl_test-0.0.2.dist-info/METADATA
duyvl_test-0.0.2.dist-info/WHEEL
duyvl_test-0.0.2.dist-info/top_level.txt
duyvl_test-0.0.2.dist-info/RECORD
