Metadata-Version: 2.2
Name: duyvl_test
Version: 0.0.2
Summary: Test Services SDK bindings
Author: DuyVL
Author-email: duyvl@vmogroup.com
Classifier: Programming Language :: Python :: 3
Classifier: License :: OSI Approved :: Apache Software License
Classifier: Operating System :: OS Independent
Requires-Python: >=3.8
Requires-Dist: grpclib>=0.4.3rc2
Requires-Dist: betterproto>=2.0.0b4
Requires-Dist: deprecation>=2.1.0
